deepdoc_pdfparser/__init__.py
deepdoc_pdfparser/parse_types.py
deepdoc_pdfparser/parser.py
deepdoc_pdfparser/utils.py
deepdoc_pdfparser/ragflow/__init__.py
deepdoc_pdfparser/ragflow/api/__init__.py
deepdoc_pdfparser/ragflow/api/settings.py
deepdoc_pdfparser/ragflow/api/db/__init__.py
deepdoc_pdfparser/ragflow/api/utils/__init__.py
deepdoc_pdfparser/ragflow/api/utils/file_utils.py
deepdoc_pdfparser/ragflow/deepdoc/__init__.py
deepdoc_pdfparser/ragflow/deepdoc/parser/__init__.py
deepdoc_pdfparser/ragflow/deepdoc/parser/pdf_parser.py
deepdoc_pdfparser/ragflow/deepdoc/parser/txt_parser.py
deepdoc_pdfparser/ragflow/deepdoc/parser/utils.py
deepdoc_pdfparser/ragflow/deepdoc/vision/__init__.py
deepdoc_pdfparser/ragflow/deepdoc/vision/layout_recognizer.py
deepdoc_pdfparser/ragflow/deepdoc/vision/ocr.py
deepdoc_pdfparser/ragflow/deepdoc/vision/operators.py
deepdoc_pdfparser/ragflow/deepdoc/vision/postprocess.py
deepdoc_pdfparser/ragflow/deepdoc/vision/recognizer.py
deepdoc_pdfparser/ragflow/deepdoc/vision/table_structure_recognizer.py
deepdoc_pdfparser/ragflow/rag/__init__.py
deepdoc_pdfparser/ragflow/rag/settings.py
deepdoc_pdfparser/ragflow/rag/app/manual.py
deepdoc_pdfparser/ragflow/rag/nlp/__init__.py
deepdoc_pdfparser/ragflow/rag/nlp/rag_tokenizer.py
deepdoc_pdfparser/ragflow/rag/res/huqie.txt
deepdoc_pdfparser/ragflow/rag/res/deepdoc/.gitattributes
deepdoc_pdfparser/ragflow/rag/res/deepdoc/README.md
deepdoc_pdfparser/ragflow/rag/res/deepdoc/ocr.res
deepdoc_pdfparser/ragflow/rag/res/deepdoc/.cache/huggingface/.gitignore
deepdoc_pdfparser/ragflow/rag/res/deepdoc/.cache/huggingface/download/.gitattributes.lock
deepdoc_pdfparser/ragflow/rag/res/deepdoc/.cache/huggingface/download/.gitattributes.metadata
deepdoc_pdfparser/ragflow/rag/res/deepdoc/.cache/huggingface/download/README.md.lock
deepdoc_pdfparser/ragflow/rag/res/deepdoc/.cache/huggingface/download/README.md.metadata
deepdoc_pdfparser/ragflow/rag/res/deepdoc/.cache/huggingface/download/det.onnx.lock
deepdoc_pdfparser-0.1.7.dist-info/METADATA
deepdoc_pdfparser-0.1.7.dist-info/WHEEL
deepdoc_pdfparser-0.1.7.dist-info/licenses/LICENSE
deepdoc_pdfparser-0.1.7.dist-info/RECORD
