Metadata-Version: 2.4
Name: deepdoc_pdfparser
Version: 0.1.7
Summary: A professional PDF parser, extracted from ragflow.deepdoc
Project-URL: Homepage, https://github.com/hedon-ai-road/deepdoc_pdfparser
Project-URL: Repository, https://github.com/hedon-ai-road/deepdoc_pdfparser.git
Project-URL: Documentation, https://github.com/hedon-ai-road/deepdoc_pdfparser#readme
Project-URL: Bug Tracker, https://github.com/hedon-ai-road/deepdoc_pdfparser/issues
Project-URL: Source Code, https://github.com/hedon-ai-road/deepdoc_pdfparser
Author-email: Hedon Wang <wjh171725713@gmail.com>
Maintainer-email: Hedon Wang <wjh171725713@gmail.com>
License: Apache-2.0
License-File: LICENSE
Keywords: artificial-intelligence,deepdoc,document,nlp,ocr,parser,pdf,ragflow
Classifier: Development Status :: 4 - Beta
Classifier: Intended Audience :: Developers
Classifier: License :: OSI Approved :: Apache Software License
Classifier: Operating System :: OS Independent
Classifier: Programming Language :: Python :: 3
Classifier: Programming Language :: Python :: 3.12
Classifier: Topic :: Office/Business :: Office Suites
Classifier: Topic :: Scientific/Engineering :: Artificial Intelligence
Classifier: Topic :: Software Development :: Libraries :: Python Modules
Classifier: Topic :: Text Processing :: Linguistic
Classifier: Topic :: Text Processing :: Markup :: HTML
Requires-Python: >=3.12
Requires-Dist: beartype>=0.21.0
Requires-Dist: beautifulsoup4>=4.13.4
Requires-Dist: bs4>=0.0.2
Requires-Dist: cn2an>=0.5.23
Requires-Dist: datasets>=3.6.0
Requires-Dist: datrie>=0.8.2
Requires-Dist: docx2txt>=0.9
Requires-Dist: dotenv>=0.9.9
Requires-Dist: hanziconv>=0.3.2
Requires-Dist: html-text>=0.7.0
Requires-Dist: huggingface-hub>=0.33.0
Requires-Dist: ipykernel>=6.29.5
Requires-Dist: jpype1>=1.5.2
Requires-Dist: langchain-community>=0.3.25
Requires-Dist: langchain-core>=0.3.65
Requires-Dist: langchain-unstructured>=0.1.6
Requires-Dist: langchain>=0.3.25
Requires-Dist: lxml>=5.4.0
Requires-Dist: numpy>=2.3.0
Requires-Dist: openai>=1.86.0
Requires-Dist: openpyxl>=3.1.5
Requires-Dist: pdf2image>=1.17.0
Requires-Dist: pdfplumber>=0.11.7
Requires-Dist: pi-heif>=0.22.0
Requires-Dist: pillow>=11.2.1
Requires-Dist: pyclipper>=1.3.0.post6
Requires-Dist: pycryptodome>=3.23.0
Requires-Dist: pycryptodomex>=3.23.0
Requires-Dist: pymupdf>=1.26.1
Requires-Dist: python-docx>=1.1.2
Requires-Dist: python-pptx>=1.0.2
Requires-Dist: ragas>=0.2.15
Requires-Dist: readability>=0.3.2
Requires-Dist: roman-numbers>=1.0.2
Requires-Dist: ruamel-yaml>=0.18.14
Requires-Dist: sentence-transformers>=4.1.0
Requires-Dist: shapely>=2.1.1
Requires-Dist: strenum>=0.4.15
Requires-Dist: trio>=0.30.0
Requires-Dist: unstructured-inference>=1.0.5
Requires-Dist: unstructured-pytesseract>=0.3.15
Requires-Dist: unstructured[pdf]>=0.17.2
Requires-Dist: word2number>=1.1
Requires-Dist: xgboost>=3.0.2
